{"type":"FeatureCollection","features":[{"type":"Feature","properties":{"marker-color":"#ff0000","marker-size":"medium","marker-symbol":"ice-cream","Placename":"Snackshot","notes":"Specialty dessert shop featuring unique and classic Hong Kong-style sweets!","link":"https://www.facebook.com/Snackshot/","Contributor":"Elana"},"geometry":{"type":"Point","coordinates":[-123.14002275466918,49.21335361062153]}},{"type":"Feature","properties":{"marker-color":"#1d7e16","marker-size":"medium","marker-symbol":"wetland","Placename":"Spit going into Semiahmoo Bay","notes":"\"Boundary Bay, Canada's top bird area, is a major stop-over on the Pacific Flyway\"","link":"https://www.birdsonthebay.ca/botb.html","Contributor":"Luke Bergmann"},"geometry":{"type":"Point","coordinates":[-122.87710189819335,49.0620569455363]}},{"type":"Feature","properties":{"marker-color":"#1d7e16","marker-symbol":"park2","Placename":"Lighthouse Point trail","notes":"Lots of very old trees!"},"geometry":{"type":"Point","coordinates":[-123.2581901550293,49.33496671391723]}}]}