{"type":"FeatureCollection","features":[{"type":"Feature","properties":{"marker-color":"#1d7e16","marker-size":"medium","marker-symbol":"wetland","Placename":"Spit going into Semiahmoo Bay","notes":"\"Boundary Bay, Canada's top bird area, is a major stop-over on the Pacific Flyway\"","link":"https://www.birdsonthebay.ca/botb.html","Contributor":"Luke Bergmann"},"geometry":{"type":"Point","coordinates":[-122.87710189819335,49.0620569455363]}},{"type":"Feature","properties":{"marker-color":"#00570e","marker-size":"medium","marker-symbol":"park2","name":"UBC Alex Fraser Research Forest","link":"https://afrf.forestry.ubc.ca/","description":"The Alex Fraser Research Forest is part of the Faculty of Forestry at the University of British Columbia.  Situated on close to 10,000 hectares of crown forest in the Cariboo region of south-central British Columbia, it is one of two UBC Research Forests managed to create opportunities for research, education and demonstration of sustainable forest management.","contributer":"Joshua Green"},"geometry":{"type":"Point","coordinates":[-122.07080841064452,52.17240519090369]}}]}