{"type":"FeatureCollection","features":[{"type":"Feature","properties":{"marker-color":"#ff0000","marker-size":"medium","marker-symbol":"ice-cream","Placename":"Snackshot","notes":"Specialty dessert shop featuring unique and classic Hong Kong-style sweets!","link":"https://www.facebook.com/Snackshot/","Contributor":"Elana"},"geometry":{"type":"Point","coordinates":[-123.14002275466918,49.21335361062153]}}]}