{"type":"FeatureCollection","features":[{"type":"Feature","properties":{"marker-color":"#1d7e16","marker-size":"medium","marker-symbol":"wetland","Placename":"Spit going into Semiahmoo Bay","notes":"\"Boundary Bay, Canada's top bird area, is a major stop-over on the Pacific Flyway\"","link":"https://www.birdsonthebay.ca/botb.html","Contributor":"Luke Bergmann"},"geometry":{"type":"Point","coordinates":[-122.87710189819335,49.0620569455363]}},{"type":"Feature","properties":{"marker-color":"#1d7e16","marker-symbol":"park2","Placename":"Lighthouse Point trail","notes":"Lots of very old trees!","marker-size":""},"geometry":{"type":"Point","coordinates":[-123.2581901550293,49.33496671391723]}},{"type":"Feature","properties":{"marker-size":"medium","marker-symbol":"star","marker-color":"#1d7e16","Placename":"Lonsdale Quay","notes":"Family-friendly pier attractions"},"geometry":{"type":"Point","coordinates":[-123.08250010013582,49.309781136835234]}}]}