{
  "type": "FeatureCollection",
  "features": [
    {
      "type": "Feature",
      "properties": {
        "marker-color": "#1d7e16",
        "marker-size": "medium",
        "marker-symbol": "wetland",
        "Placename": "Semiahmoo Bay (Blackie Spit)",
        "notes": "\"Boundary Bay, Canada's top bird area, is a major stop-over on the Pacific Flyway\"",
        "link": "https://www.birdsonthebay.ca/botb.html",
        "Contributor": "Luke Bergmann"
      },
      "geometry": {
        "type": "Point",
        "coordinates": [
          -122.87710189819335,
          49.0620569455363
        ]
      }
    }
    ]
}
